LICENSE.txt
README.md
setup.cfg
setup.py
mwk_logger/__init__.py
mwk_logger/decorators.py
mwk_logger/logger.py
mwk_logger.egg-info/PKG-INFO
mwk_logger.egg-info/SOURCES.txt
mwk_logger.egg-info/dependency_links.txt
mwk_logger.egg-info/top_level.txt