Metadata-Version: 2.1
Name: mwk-logger
Version: 2.0.4
Summary: Custom logger with colors on terminal and some useful decorators
Home-page: https://github.com/MWKSolution/mwk-logger
Author: MWK Solution
Author-email: mjwk1020@gmail.com
License: MIT
Platform: any
Classifier: Development Status :: 4 - Beta
Classifier: License :: OSI Approved :: MIT License
Classifier: Programming Language :: Python :: 3
Requires-Python: >=3.5
License-File: LICENSE.txt
